surfgraph/__init__.py
surfgraph/chemical_environment.py
surfgraph/helpers.py
surfgraph/populate_folders.py
surfgraph/site_detection.py
surfgraph/test.py
surfgraph-0.3.1.data/scripts/analyze_chem_env.py
surfgraph-0.3.1.data/scripts/generate_sites.py
surfgraph-0.3.1.dist-info/DESCRIPTION.rst
surfgraph-0.3.1.dist-info/METADATA
surfgraph-0.3.1.dist-info/RECORD
surfgraph-0.3.1.dist-info/WHEEL
surfgraph-0.3.1.dist-info/metadata.json
surfgraph-0.3.1.dist-info/top_level.txt
