Metadata-Version: 2.0
Name: surfgraph
Version: 0.3.1
Summary: A package for generating chemical environment graphs of surfaces
Home-page: UNKNOWN
Author: Tristan Maxson, Siddharth Deshpande
Author-email: tgmaxson@gmail.com, sidd20111992@gmail.com
License: UNKNOWN
Platform: UNKNOWN
Classifier: Intended Audience :: Science/Research
Classifier: Programming Language :: Python :: 3
Classifier: Topic :: Scientific/Engineering :: Chemistry
Classifier: Topic :: Scientific/Engineering :: Physics
Classifier: Topic :: Scientific/Engineering
Classifier: License :: OSI Approved :: GNU Lesser General Public License v2 or later (LGPLv2+)
Classifier: Framework :: Matplotlib
Requires-Python: >=3
Requires-Dist: numpy (>=1.11.3)
Requires-Dist: networkx (>=2.5)
Requires-Dist: matplotlib (>=2.0.0)
Requires-Dist: ase (>=3.19.1)
